babelbond/__init__.py
babelbond/babelbond.py
babelbond/cli.py
babelbond-0.1.2.dist-info/licenses/LICENSE
babelbond-0.1.2.dist-info/METADATA
babelbond-0.1.2.dist-info/WHEEL
babelbond-0.1.2.dist-info/top_level.txt
babelbond-0.1.2.dist-info/RECORD
