Metadata-Version: 2.4
Name: babelbond
Version: 0.1.2
Summary: BabelBond CLI
Author-email: BabelBond <contact@babelbond.com>
Maintainer-email: BabelBond <contact@babelbond.com>
License: GNU General Public License v3
Project-URL: bugs, https://github.com/babelbond/babelbond/issues
Project-URL: changelog, https://github.com/babelbond/babelbond/blob/master/changelog.md
Project-URL: homepage, https://github.com/babelbond/babelbond
License-File: LICENSE
Requires-Dist: typer
Provides-Extra: dev
Requires-Dist: coverage; extra == "dev"
Requires-Dist: mypy; extra == "dev"
Requires-Dist: pytest; extra == "dev"
Requires-Dist: ruff; extra == "dev"
Dynamic: license-file
